pydatajson/__init__.py
pydatajson/__main__.py
pydatajson/backup.py
pydatajson/catalog_readme.py
pydatajson/ckan_reader.py
pydatajson/ckan_utils.py
pydatajson/constants.py
pydatajson/core.py
pydatajson/custom_exceptions.py
pydatajson/custom_remote_ckan.py
pydatajson/documentation.py
pydatajson/download.py
pydatajson/federation.py
pydatajson/federation_indicators_generator.py
pydatajson/helpers.py
pydatajson/indicators.py
pydatajson/readers.py
pydatajson/reporting.py
pydatajson/search.py
pydatajson/status_indicators_generator.py
pydatajson/threading_helper.py
pydatajson/time_series.py
pydatajson/transformation.py
pydatajson/validation.py
pydatajson/writers.py
pydatajson/fields/fields.json
pydatajson/response_formatters/__init__.py
pydatajson/response_formatters/dict_formatter.py
pydatajson/response_formatters/list_formatter.py
pydatajson/response_formatters/tables_formatter.py
pydatajson/response_formatters/validation_response_formatter.py
pydatajson/schemas/accrualPeriodicity.json
pydatajson/schemas/catalog.json
pydatajson/schemas/dataset.json
pydatajson/schemas/distribution.json
pydatajson/schemas/field.json
pydatajson/schemas/mixed-types.json
pydatajson/schemas/required_fields_schema.json
pydatajson/schemas/superThemeTaxonomy.json
pydatajson/schemas/theme.json
pydatajson/templates/catalog_readme.txt
pydatajson/validators/__init__.py
pydatajson/validators/consistent_distribution_fields_validator.py
pydatajson/validators/distribution_download_urls_validator.py
pydatajson/validators/distribution_urls_validator.py
pydatajson/validators/landing_pages_validator.py
pydatajson/validators/simple_validator.py
pydatajson/validators/theme_ids_not_repeated_validator.py
pydatajson/validators/url_validator.py
pydatajson-0.4.67.dist-info/LICENSE
pydatajson-0.4.67.dist-info/METADATA
pydatajson-0.4.67.dist-info/WHEEL
pydatajson-0.4.67.dist-info/entry_points.txt
pydatajson-0.4.67.dist-info/top_level.txt
pydatajson-0.4.67.dist-info/RECORD
