Metadata-Version: 2.1
Name: pydatajson
Version: 0.4.67
Summary: Paquete en python con herramientas para generar y validar metadatos de catálogos de datos en formato data.json.
Home-page: https://github.com/datosgobar/pydatajson
Author: Datos Argentina
Author-email: datos@modernizacion.gob.ar
License: MIT license
Keywords: pydatajson
Platform: UNKNOWN
Classifier: Development Status :: 2 - Pre-Alpha
Classifier: Intended Audience :: Developers
Classifier: License :: OSI Approved :: MIT License
Classifier: Natural Language :: English
Classifier: Programming Language :: Python :: 2
Classifier: Programming Language :: Python :: 2.7
Classifier: Programming Language :: Python :: 3
Classifier: Programming Language :: Python :: 3.6
